planck/CNAME
planck/__init__.py
planck/_common.py
planck/_scipy.py
planck/_version.py
planck/constants.py
planck/units.py
planck/models/__init__.py
planck/models/dimensionalphysicalconstant.py
planck/models/nondimensionalphysicalconstant.py
planck/models/unit.py
planck-0.0.8.dist-info/LICENSE
planck-0.0.8.dist-info/METADATA
planck-0.0.8.dist-info/WHEEL
planck-0.0.8.dist-info/top_level.txt
planck-0.0.8.dist-info/RECORD
