Metadata-Version: 2.1
Name: planck
Version: 0.0.8
Summary: Physical constants and unit conversion.
Author-email: Olivier Soucy <olivier.soucy@okube.ai>
License: MIT
Project-URL: Homepage, https://www.okube.ai/planck/
Project-URL: Bug Tracker, https://github.com/okube-ai/planck/issues
Keywords: one,two
Classifier: Development Status :: 4 - Beta
Classifier: Programming Language :: Python :: 3
Classifier: License :: OSI Approved :: MIT License
Classifier: Operating System :: OS Independent
Classifier: Programming Language :: Python :: 3
Classifier: Programming Language :: Python :: 3.9
Classifier: Programming Language :: Python :: 3.10
Classifier: Programming Language :: Python :: 3.11
Classifier: Programming Language :: Python :: 3.12
Classifier: Programming Language :: Python :: 3.13
Requires-Python: >=3.9
License-File: LICENSE
Provides-Extra: numpy
Requires-Dist: numpy; extra == "numpy"
Provides-Extra: dev
Requires-Dist: black; extra == "dev"
Requires-Dist: mkdocs; extra == "dev"
Requires-Dist: mkdocstrings[python]; extra == "dev"
Requires-Dist: mkdocs-material; extra == "dev"
Provides-Extra: test
Requires-Dist: pytest; extra == "test"
Requires-Dist: pytest-cov; extra == "test"
Requires-Dist: pytest-examples; extra == "test"
